pyield/__about__.py
pyield/__init__.py
pyield/clock.py
pyield/conftest.py
pyield/converters.py
pyield/data_cache.py
pyield/fwd.py
pyield/interpolator.py
pyield/py.typed
pyield/retry.py
pyield/types.py
pyield/anbima/__init__.py
pyield/anbima/difusao.py
pyield/anbima/ettj_intraday.py
pyield/anbima/ettj_last.py
pyield/anbima/ima.py
pyield/anbima/imaq.py
pyield/anbima/tpf.py
pyield/b3/__init__.py
pyield/b3/common.py
pyield/b3/di1.py
pyield/b3/di_over.py
pyield/b3/price_report.py
pyield/b3/futures/__init__.py
pyield/b3/futures/core.py
pyield/b3/futures/intraday.py
pyield/b3/futures/historical/core.py
pyield/b3/futures/historical/historical_b3.py
pyield/b3/futures/historical/historical_bmf.py
pyield/bc/__init__.py
pyield/bc/auction.py
pyield/bc/ptax_api.py
pyield/bc/rates.py
pyield/bc/repo.py
pyield/bc/trades_intraday.py
pyield/bc/trades_monthly.py
pyield/bc/vna.py
pyield/bday/__init__.py
pyield/bday/core.py
pyield/bday/holidays/__init__.py
pyield/bday/holidays/br_holidays_new.txt
pyield/bday/holidays/br_holidays_old.txt
pyield/bday/holidays/brholidays.py
pyield/ipca/__init__.py
pyield/ipca/historical.py
pyield/ipca/projected.py
pyield/tn/__init__.py
pyield/tn/auctions.py
pyield/tn/benchmark.py
pyield/tn/lft.py
pyield/tn/ltn.py
pyield/tn/ntnb.py
pyield/tn/ntnb1.py
pyield/tn/ntnbprinc.py
pyield/tn/ntnc.py
pyield/tn/ntnf.py
pyield/tn/pre.py
pyield/tn/tools.py
pyield-0.42.7.dist-info/METADATA
pyield-0.42.7.dist-info/WHEEL
pyield-0.42.7.dist-info/licenses/LICENSE
pyield-0.42.7.dist-info/RECORD
