Metadata-Version: 2.4
Name: pyield
Version: 0.42.7
Summary: A Python library for analysis of fixed income instruments in Brazil
Project-URL: Homepage, https://github.com/crdcj/PYield
Project-URL: Documentation, https://crdcj.github.io/PYield
Project-URL: Source, https://github.com/crdcj/PYield
Project-URL: Bug Tracker, https://github.com/crdcj/PYield/issues
Author-email: Carlos Carvalho <cr.cj@outlook.com>
License: MIT License
License-File: LICENSE
Keywords: analysis,bonds,brazil,finance,fixed-income
Classifier: Intended Audience :: Financial and Insurance Industry
Classifier: License :: OSI Approved :: MIT License
Classifier: Operating System :: OS Independent
Classifier: Programming Language :: Python :: 3
Classifier: Topic :: Office/Business :: Financial :: Investment
Requires-Python: >=3.12
Requires-Dist: lxml>=6.0.0
Requires-Dist: polars[pyarrow]>=1.33.0
Requires-Dist: python-dateutil>=2.8.0
Requires-Dist: requests>=2.31.0
Requires-Dist: tenacity>=9.0.0
